LICENSE
MANIFEST.in
README.rst
pyproject.toml
requirements.txt
setup.py
discord/__init__.py
discord/abc.py
discord/activity.py
discord/appinfo.py
discord/asset.py
discord/audit_logs.py
discord/backoff.py
discord/channel.py
discord/client.py
discord/colour.py
discord/components.py
discord/context_managers.py
discord/cooldowns.py
discord/embeds.py
discord/emoji.py
discord/enums.py
discord/errors.py
discord/file.py
discord/flags.py
discord/gateway.py
discord/guild.py
discord/health_check.py
discord/http.py
discord/integrations.py
discord/interactions.py
discord/invite.py
discord/iterators.py
discord/member.py
discord/mentions.py
discord/message.py
discord/mixins.py
discord/object.py
discord/oggparse.py
discord/opus.py
discord/partial_emoji.py
discord/permissions.py
discord/player.py
discord/raw_models.py
discord/reaction.py
discord/role.py
discord/shard.py
discord/stage_instance.py
discord/state.py
discord/sticker.py
discord/team.py
discord/template.py
discord/threads.py
discord/user.py
discord/utils.py
discord/voice_client.py
discord/welcome_screen.py
discord/widget.py
discord/ext/commands/__init__.py
discord/ext/commands/bot.py
discord/ext/tasks/__init__.py
discord/types/__init__.py
discord/types/activity.py
discord/types/appinfo.py
discord/types/audit_log.py
discord/types/channel.py
discord/types/components.py
discord/types/embed.py
discord/types/emoji.py
discord/types/gateway.py
discord/types/guild.py
discord/types/integration.py
discord/types/interactions.py
discord/types/invite.py
discord/types/member.py
discord/types/message.py
discord/types/raw_models.py
discord/types/role.py
discord/types/snowflake.py
discord/types/sticker.py
discord/types/team.py
discord/types/template.py
discord/types/threads.py
discord/types/user.py
discord/types/voice.py
discord/types/webhook.py
discord/types/welcome_screen.py
discord/types/widget.py
discord/ui/__init__.py
discord/ui/button.py
discord/ui/item.py
discord/ui/select.py
discord/ui/view.py
discord/webhook/__init__.py
nextcordunaliased.py.egg-info/PKG-INFO
nextcordunaliased.py.egg-info/SOURCES.txt
nextcordunaliased.py.egg-info/dependency_links.txt
nextcordunaliased.py.egg-info/requires.txt
nextcordunaliased.py.egg-info/top_level.txt