Metadata-Version: 2.1
Name: nextcordunaliased.py
Version: 2.0.0a2
Summary: A Python wrapper for the Discord API forked from discord.py
Home-page: https://github.com/nextcord/nextcord
Author: tag-epic & Rapptz
License: MIT
Project-URL: Documentation, https://nextcord.readthedocs.io/en/latest/
Project-URL: Issue tracker, https://github.com/nextcord/nextcord/issues
Platform: UNKNOWN
Classifier: Development Status :: 5 - Production/Stable
Classifier: License :: OSI Approved :: MIT License
Classifier: Intended Audience :: Developers
Classifier: Natural Language :: English
Classifier: Operating System :: OS Independent
Classifier: Programming Language :: Python :: 3.8
Classifier: Programming Language :: Python :: 3.9
Classifier: Topic :: Internet
Classifier: Topic :: Software Development :: Libraries
Classifier: Topic :: Software Development :: Libraries :: Python Modules
Classifier: Topic :: Utilities
Classifier: Typing :: Typed
Obsoletes: nextcord
Obsoletes: nextcord.py
Obsoletes: nextcordunaliased
Obsoletes: discord
Obsoletes: discord.py
Requires-Python: >=3.8.0
Provides-Extra: voice
Provides-Extra: docs
Provides-Extra: speed
